nonebot_plugin_translator/__init__.py
nonebot_plugin_translator-2.0.0a8.post0.dist-info/LICENSE
nonebot_plugin_translator-2.0.0a8.post0.dist-info/WHEEL
nonebot_plugin_translator-2.0.0a8.post0.dist-info/METADATA
nonebot_plugin_translator-2.0.0a8.post0.dist-info/RECORD
